mcp_echo/__init__.py
mcp_echo/server.py
mcp_echo/test.py
mcp_echo-0.2.0.dist-info/licenses/LICENSE
mcp_echo-0.2.0.dist-info/METADATA
mcp_echo-0.2.0.dist-info/WHEEL
mcp_echo-0.2.0.dist-info/entry_points.txt
mcp_echo-0.2.0.dist-info/top_level.txt
mcp_echo-0.2.0.dist-info/RECORD
