Metadata-Version: 2.4
Name: mcp-echo
Version: 0.2.0
Summary: 一个简单的MCP服务器，提供echo功能：输入什么就返回什么。支持延迟返回功能。
Home-page: https://github.com/BACH-AI-Tools/mcp-echo
Author: Bach Studio
Author-email: Bach Studio <contact@bachstudio.com>
License: MIT
Project-URL: Homepage, https://github.com/BACH-AI-Tools/mcp-echo
Project-URL: Repository, https://github.com/BACH-AI-Tools/mcp-echo
Project-URL: Issues, https://github.com/BACH-AI-Tools/mcp-echo/issues
Keywords: mcp,echo,model-context-protocol,bachstudio
Classifier: Development Status :: 4 - Beta
Classifier: Intended Audience :: Developers
Classifier: Topic :: Software Development :: Libraries :: Python Modules
Classifier: License :: OSI Approved :: MIT License
Classifier: Programming Language :: Python :: 3
Classifier: Programming Language :: Python :: 3.10
Classifier: Programming Language :: Python :: 3.11
Classifier: Programming Language :: Python :: 3.12
Requires-Python: >=3.10
License-File: LICENSE
Requires-Dist: mcp>=0.9.0
Dynamic: author
Dynamic: home-page
Dynamic: license-file
Dynamic: requires-python
